transplant/ZMQ.m
transplant/__init__.py
transplant/base64decode.m
transplant/base64encode.m
transplant/dumpjson.m
transplant/dumpmsgpack.m
transplant/parsejson.m
transplant/parsemsgpack.m
transplant/test_transplant.py
transplant/transplant_master.py
transplant/transplant_remote.m
transplant/transplant_remote.py
transplant/transplantzmq.h
Transplant-0.8.11.dist-info/LICENSE
Transplant-0.8.11.dist-info/METADATA
Transplant-0.8.11.dist-info/WHEEL
Transplant-0.8.11.dist-info/top_level.txt
Transplant-0.8.11.dist-info/RECORD
