Metadata-Version: 2.1
Name: Transplant
Version: 0.8.11
Summary: Call Matlab from Python (requires Matlab)
Home-page: https://github.com/bastibe/transplant
Author: Bastian Bechtold
Author-email: basti@bastibe.de
License: BSD 3-clause
Platform: UNKNOWN
Classifier: Development Status :: 4 - Beta
Classifier: Intended Audience :: Science/Research
Classifier: License :: OSI Approved :: BSD License
Classifier: Operating System :: MacOS
Classifier: Operating System :: Microsoft :: Windows
Classifier: Operating System :: POSIX :: Linux
Classifier: Programming Language :: Python :: 3.4
Classifier: Programming Language :: Python :: 3.5
Classifier: Programming Language :: Python :: 3.6
Classifier: Programming Language :: Python :: 3.7
Requires: matlab
Requires: libzmq
Requires-Python: >=3.4
Requires-Dist: numpy
Requires-Dist: pyzmq
Requires-Dist: msgpack
